{"2000": {"Downhill": {"points": 1, "n": 1}}, "2002": {"Downhill": {"points": 218, "n": 10}, "Super G": {"points": 43, "n": 5}}, "2003": {"Downhill": {"points": 317, "n": 11}, "Super G": {"points": 8, "n": 2}}, "2004": {"Downhill": {"points": 290, "n": 12}}, "2005": {"Downhill": {"points": 155, "n": 11}}, "2006": {"Downhill": {"points": 216, "n": 9}, "Super G": {"points": 67, "n": 2}}, "2007": {"Downhill": {"points": 158, "n": 11}}, "2008": {"Downhill": {"points": 232, "n": 9}}, "2009": {"Downhill": {"points": 424, "n": 9}, "Super G": {"points": 142, "n": 5}}, "2010": {"Downhill": {"points": 179, "n": 8}, "Super G": {"points": 50, "n": 6}}, "2011": {"Downhill": {"points": 411, "n": 9}, "Super G": {"points": 168, "n": 6}}, "2012": {"Downhill": {"points": 605, "n": 11}, "Super G": {"points": 318, "n": 8}}, "2013": {"Downhill": {"points": 381, "n": 8}, "Super G": {"points": 104, "n": 5}}, "2014": {"Downhill": {"points": 175, "n": 9}, "Super G": {"points": 17, "n": 5}}, "2015": {"Downhill": {"points": 104, "n": 10}, "Super G": {"points": 0, "n": 2}}, "2016": {"Downhill": {"points": 156, "n": 11}, "Super G": {"points": 9, "n": 6}}, "2017": {"Downhill": {"points": 55, "n": 7}}}