{"1991": {"Combined": {"points": 3, "n": 1}, "Giant Slalom": {"points": 5, "n": 1}, "Slalom": {"points": 6, "n": 1}, "Super G": {"points": 2, "n": 1}}, "1992": {"Combined": {"points": 40, "n": 1}, "Giant Slalom": {"points": 3, "n": 1}, "Slalom": {"points": 5, "n": 1}, "Super G": {"points": 23, "n": 3}}, "1993": {"Combined": {"points": 24, "n": 1}, "Slalom": {"points": 194, "n": 6}}, "1995": {"Giant Slalom": {"points": 16, "n": 1}, "Slalom": {"points": 20, "n": 2}}, "1996": {"Giant Slalom": {"points": 68, "n": 5}, "Slalom": {"points": 139, "n": 6}}, "1997": {"Giant Slalom": {"points": 37, "n": 2}, "Slalom": {"points": 62, "n": 4}}, "1998": {"Giant Slalom": {"points": 41, "n": 5}, "Slalom": {"points": 38, "n": 3}}, "1999": {"Giant Slalom": {"points": 118, "n": 6}, "Slalom": {"points": 169, "n": 7}}, "2000": {"Giant Slalom": {"points": 57, "n": 5}, "Slalom": {"points": 279, "n": 9}}, "2001": {"Giant Slalom": {"points": 7, "n": 3}, "Slalom": {"points": 340, "n": 9}}, "2002": {"Giant Slalom": {"points": 0, "n": 1}, "Slalom": {"points": 26, "n": 2}}}