{"1989": {"Combined": {"points": 4, "n": 1}, "Downhill": {"points": 8, "n": 2}}, "1990": {"Combined": {"points": 8, "n": 1}, "Downhill": {"points": 12, "n": 2}}, "1991": {"Downhill": {"points": 7, "n": 2}, "Super G": {"points": 6, "n": 1}}, "1992": {"Combined": {"points": 31, "n": 1}, "Downhill": {"points": 47, "n": 4}, "Super G": {"points": 32, "n": 2}}, "1993": {"Combined": {"points": 18, "n": 1}, "Downhill": {"points": 39, "n": 2}}, "1994": {"Downhill": {"points": 168, "n": 4}, "Super G": {"points": 22, "n": 1}}, "1995": {"Downhill": {"points": 44, "n": 6}}}