{"1999": {"Downhill": {"points": 5, "n": 1}}, "2000": {"Super G": {"points": 4, "n": 2}}, "2001": {"Downhill": {"points": 0, "n": 4}, "Giant Slalom": {"points": 0, "n": 1}, "Super G": {"points": 5, "n": 4}}, "2002": {"Downhill": {"points": 6, "n": 7}, "Super G": {"points": 0, "n": 3}}, "2003": {"Downhill": {"points": 38, "n": 10}, "Super G": {"points": 32, "n": 4}}, "2004": {"Downhill": {"points": 2, "n": 11}, "Super G": {"points": 38, "n": 6}}, "2005": {"Downhill": {"points": 0, "n": 4}, "Super G": {"points": 0, "n": 3}}}