{"2000": {"Super G": {"points": 11, "n": 1}}, "2001": {"Super G": {"points": 0, "n": 1}}, "2002": {"Giant Slalom": {"points": 0, "n": 1}}, "2003": {"Downhill": {"points": 68, "n": 6}, "Giant Slalom": {"points": 0, "n": 1}, "Super G": {"points": 6, "n": 7}}, "2004": {"Downhill": {"points": 66, "n": 8}, "Giant Slalom": {"points": 0, "n": 3}, "Super G": {"points": 9, "n": 5}}, "2005": {"Downhill": {"points": 14, "n": 7}, "Super G": {"points": 4, "n": 7}}, "2006": {"Downhill": {"points": 0, "n": 2}, "Super G": {"points": 79, "n": 7}}, "2007": {"Downhill": {"points": 21, "n": 6}, "Giant Slalom": {"points": 0, "n": 1}, "Super G": {"points": 109, "n": 6}}, "2008": {"Downhill": {"points": 34, "n": 6}, "Super G": {"points": 0, "n": 4}}}