{"1996": {"Giant Slalom": {"points": 22, "n": 1}}, "1999": {"Slalom": {"points": 97, "n": 4}}, "2000": {"Giant Slalom": {"points": 42, "n": 2}, "Slalom": {"points": 307, "n": 9}}, "2001": {"Giant Slalom": {"points": 37, "n": 8}, "Slalom": {"points": 226, "n": 9}}, "2002": {"Slalom": {"points": 318, "n": 9}}, "2003": {"Giant Slalom": {"points": 54, "n": 8}, "Slalom": {"points": 473, "n": 10}}, "2004": {"Giant Slalom": {"points": 97, "n": 7}, "Slalom": {"points": 630, "n": 11}}, "2005": {"Giant Slalom": {"points": 89, "n": 8}, "Slalom": {"points": 408, "n": 9}}, "2006": {"Combined": {"points": 182, "n": 3}, "Giant Slalom": {"points": 169, "n": 8}, "Slalom": {"points": 198, "n": 10}, "Super G": {"points": 18, "n": 1}}, "2007": {"Combined": {"points": 106, "n": 3}, "Giant Slalom": {"points": 92, "n": 6}, "Slalom": {"points": 86, "n": 9}}, "2008": {"Combined": {"points": 206, "n": 5}, "Downhill": {"points": 66, "n": 4}, "Giant Slalom": {"points": 86, "n": 7}, "Slalom": {"points": 159, "n": 9}, "Super G": {"points": 17, "n": 2}}, "2009": {"Combined": {"points": 0, "n": 1}, "Giant Slalom": {"points": 6, "n": 3}, "Slalom": {"points": 8, "n": 3}}, "2010": {"Slalom": {"points": 11, "n": 4}}, "2011": {"Slalom": {"points": 0, "n": 7}}, "2012": {"Slalom": {"points": 18, "n": 10}}, "2013": {"Slalom": {"points": 0, "n": 7}}}